[
  {
    "cardId": 1,
    "cardItem": "mercury"
  },
  {
    "cardId": 2,
    "cardItem": "mercury"
  },
  {
    "cardId": 3,
    "cardItem": "venus"
  },
  {
    "cardId": 4,
    "cardItem": "venus"
  },
  {
    "cardId": 5,
    "cardItem": "earth"
  },
  {
    "cardId": 6,
    "cardItem": "earth"
  },
  {
    "cardId": 7,
    "cardItem": "mars"
  },
  {
    "cardId": 8,
    "cardItem": "mars"
  },
  {
    "cardId": 9,
    "cardItem": "jupiter"
  },
  {
    "cardId": 10,
    "cardItem": "jupiter"
  },
  {
    "cardId": 11,
    "cardItem": "saturn"
  },
  {
    "cardId": 12,
    "cardItem": "saturn"
  },
  {
    "cardId": 13,
    "cardItem": "uranus"
  },
  {
    "cardId": 14,
    "cardItem": "uranus"
  },
  {
    "cardId": 15,
    "cardItem": "neptune"
  },
  {
    "cardId": 16,
    "cardItem": "neptune"
  }
]
